vcfcache/__init__.py
vcfcache/__main__.py
vcfcache/cli.py
vcfcache/compare.py
vcfcache/demo.py
vcfcache/database/__init__.py
vcfcache/database/annotator.py
vcfcache/database/base.py
vcfcache/database/initializer.py
vcfcache/database/outputs.py
vcfcache/database/updater.py
vcfcache/database/workflow_base.py
vcfcache/database/workflow_manager.py
vcfcache/demo_data/demo_annotation.yaml
vcfcache/demo_data/demo_bp.bcf
vcfcache/demo_data/demo_bp.bcf.csi
vcfcache/demo_data/demo_bpext.bcf
vcfcache/demo_data/demo_bpext.bcf.csi
vcfcache/demo_data/demo_params.yaml
vcfcache/demo_data/demo_sample.vcf.gz
vcfcache/demo_data/demo_sample.vcf.gz.csi
vcfcache/integrations/__init__.py
vcfcache/integrations/zenodo.py
vcfcache/recipes/docker-annotated/annotation.yaml
vcfcache/recipes/docker-annotated/params.yaml
vcfcache/recipes/docker-cache/annotation.yaml
vcfcache/recipes/docker-cache/params.yaml
vcfcache/recipes/grch37_vep115.2_apptainer/README.md
vcfcache/recipes/grch37_vep115.2_apptainer/annotation.yaml
vcfcache/recipes/grch37_vep115.2_apptainer/params.yaml
vcfcache/recipes/hg38_vep115.2/params.yaml
vcfcache/recipes/hg38_vep115_complete/README.md
vcfcache/recipes/hg38_vep115_complete/params.yaml
vcfcache/utils/__init__.py
vcfcache/utils/archive.py
vcfcache/utils/completion.py
vcfcache/utils/logging.py
vcfcache/utils/naming.py
vcfcache/utils/paths.py
vcfcache/utils/schemas.py
vcfcache/utils/validation.py
vcfcache-0.5.3.dist-info/METADATA
vcfcache-0.5.3.dist-info/WHEEL
vcfcache-0.5.3.dist-info/entry_points.txt
vcfcache-0.5.3.dist-info/licenses/LICENSE
vcfcache-0.5.3.dist-info/RECORD
