Metadata-Version: 2.4
Name: vcfcache
Version: 0.5.3
Summary: Cache-based VCF annotation accelerator
Project-URL: Homepage, https://github.com/julius-muller/vcfcache
Project-URL: Source, https://github.com/julius-muller/vcfcache
Project-URL: Issues, https://github.com/julius-muller/vcfcache/issues
Author-email: Julius Müller <julius.mueller@dkfz-heidelberg.de>
License: GPL-3.0-only
License-File: LICENSE
Classifier: Intended Audience :: Science/Research
Classifier: License :: OSI Approved :: GNU General Public License v3 (GPLv3)
Classifier: Operating System :: POSIX :: Linux
Classifier: Programming Language :: Python :: 3
Classifier: Programming Language :: Python :: 3 :: Only
Classifier: Topic :: Scientific/Engineering :: Bio-Informatics
Requires-Python: >=3.11
Requires-Dist: click>=8.0.0
Requires-Dist: pysam>=0.22.0
Requires-Dist: pyyaml>=6.0.0
Requires-Dist: requests>=2.20.0
Provides-Extra: dev
Requires-Dist: black>=25.12.0; extra == 'dev'
Requires-Dist: mypy>=1.19.0; extra == 'dev'
Requires-Dist: pandas>=2.2.0; extra == 'dev'
Requires-Dist: pyarrow>=20.0.0; extra == 'dev'
Requires-Dist: pytest-cov>=6.0.0; extra == 'dev'
Requires-Dist: pytest>=9.0.2; extra == 'dev'
Requires-Dist: ruff>=0.14.8; extra == 'dev'
Requires-Dist: twine>=4.0.0; extra == 'dev'
Provides-Extra: gnomad
Requires-Dist: hail>=0.2.0; extra == 'gnomad'
Provides-Extra: parquet
Requires-Dist: pandas>=2.2.0; extra == 'parquet'
Requires-Dist: pyarrow>=20.0.0; extra == 'parquet'
